<?xml version="1.0" encoding="UTF-8"?>
<MF0 version="1.1" packageUris="http://schema.mathworks.com/mf0/ci/19700101 http://schema.mathworks.com/mf0/sl_modelref_info/R2022a http://schema.mathworks.com/mf0/slexec_mm_sto/R2022a_202107291127">
  <ModelRefInfoRepo.ModelRefInfoRoot type="ModelRefInfoRepo.ModelRefInfoRoot" uuid="45207491-961e-4a97-a674-e8121be27609">
    <allEdges type="ModelRefInfoRepo.SampleTimeGraphEdge" uuid="84610bc6-601c-4021-9419-6f2314299a7a">
      <dstNodeIdx>1</dstNodeIdx>
    </allEdges>
    <allEdges type="ModelRefInfoRepo.SampleTimeGraphEdge" uuid="ee378d84-1c65-4744-8d95-fa9a409157d7">
      <dstNodeIdx>2</dstNodeIdx>
    </allEdges>
    <allEdges type="ModelRefInfoRepo.SampleTimeGraphEdge" uuid="374d8885-9e38-4e03-84fd-50605a6e8269">
      <dstNodeIdx>3</dstNodeIdx>
    </allEdges>
    <allEdges type="ModelRefInfoRepo.SampleTimeGraphEdge" uuid="7a813007-d497-471e-9519-e63b1fffd8b1">
      <dstNodeIdx>4</dstNodeIdx>
    </allEdges>
    <allEdges type="ModelRefInfoRepo.SampleTimeGraphEdge" uuid="3e305ddc-d78a-437c-b1a9-0f277b268296">
      <dstNodeIdx>5</dstNodeIdx>
    </allEdges>
    <allEdges type="ModelRefInfoRepo.SampleTimeGraphEdge" uuid="25917b48-df8b-4e3a-9a77-693ad7a6c8fb">
      <dstNodeIdx>6</dstNodeIdx>
    </allEdges>
    <allEdges type="ModelRefInfoRepo.SampleTimeGraphEdge" uuid="cd7f935c-48ba-4738-a163-9d3c8b099e95">
      <dstNodeIdx>7</dstNodeIdx>
    </allEdges>
    <allEdges type="ModelRefInfoRepo.SampleTimeGraphEdge" uuid="cb42b313-149e-4394-9a76-6f60e2796297">
      <dstNodeIdx>8</dstNodeIdx>
    </allEdges>
    <allEdges type="ModelRefInfoRepo.SampleTimeGraphEdge" uuid="13742b2a-9fd7-4d23-86c2-0069f712603b">
      <dstNodeIdx>9</dstNodeIdx>
    </allEdges>
    <allEdges type="ModelRefInfoRepo.SampleTimeGraphEdge" uuid="974bde4a-fd41-489c-beea-a77aaa3f7eeb">
      <dstNodeIdx>10</dstNodeIdx>
    </allEdges>
    <allEdges type="ModelRefInfoRepo.SampleTimeGraphEdge" uuid="72c897d0-0425-4140-b8b4-b99ce6916387">
      <dstNodeIdx>11</dstNodeIdx>
    </allEdges>
    <allEdges type="ModelRefInfoRepo.SampleTimeGraphEdge" uuid="f7436a11-2159-459e-af40-7186613957d6">
      <dstNodeIdx>12</dstNodeIdx>
    </allEdges>
    <allEdges type="ModelRefInfoRepo.SampleTimeGraphEdge" uuid="87741585-7f22-4af5-a83d-bf3be31f5b03">
      <dstNodeIdx>13</dstNodeIdx>
    </allEdges>
    <allEdges type="ModelRefInfoRepo.SampleTimeGraphEdge" uuid="2dd4d1d5-8cbb-4d7d-87bf-0bfb9b1c073a">
      <dstNodeIdx>14</dstNodeIdx>
    </allEdges>
    <allEdges type="ModelRefInfoRepo.SampleTimeGraphEdge" uuid="945f1563-fbe5-4df8-bc4b-a08883d2ed63">
      <dstNodeIdx>15</dstNodeIdx>
    </allEdges>
    <allEdges type="ModelRefInfoRepo.SampleTimeGraphEdge" uuid="8367e043-aafe-40a1-beb5-6f2ae108119e">
      <dstNodeIdx>16</dstNodeIdx>
    </allEdges>
    <allEdges type="ModelRefInfoRepo.SampleTimeGraphEdge" uuid="43f74139-655a-48aa-a732-5377e87d9bae">
      <dstNodeIdx>17</dstNodeIdx>
    </allEdges>
    <allEdges type="ModelRefInfoRepo.SampleTimeGraphEdge" uuid="c332e316-a43b-4115-8dc9-eae74b79b1b1">
      <dstNodeIdx>18</dstNodeIdx>
    </allEdges>
    <allEdges type="ModelRefInfoRepo.SampleTimeGraphEdge" uuid="7294698b-e368-41f0-a962-485cd06b34bd">
      <dstNodeIdx>19</dstNodeIdx>
    </allEdges>
    <allEdges type="ModelRefInfoRepo.SampleTimeGraphEdge" uuid="8387814f-ebfe-4693-8f1c-4dc8ecce26d4">
      <dstNodeIdx>20</dstNodeIdx>
    </allEdges>
    <allEdges type="ModelRefInfoRepo.SampleTimeGraphEdge" uuid="55cc6f37-5b76-4ed0-a870-25bc03661f9a">
      <dstNodeIdx>21</dstNodeIdx>
    </allEdges>
    <childModelRefInfo type="ModelRefInfoRepo.ChildModelRefInfo" uuid="8f95b230-3485-45c1-be34-a31ded0ca801">
      <isSingleInstance>true</isSingleInstance>
      <modelName>DHM</modelName>
      <modelPath>DHM</modelPath>
    </childModelRefInfo>
    <containsInitResetTermSampleTimes>true</containsInitResetTermSampleTimes>
    <dataDictionary>DHM.sldd</dataDictionary>
    <dataDictionarySet>DHM.sldd</dataDictionarySet>
    <dataDictionarySetForDataTypeCheck>DHM.sldd</dataDictionarySetForDataTypeCheck>
    <dataTransferInfos>AAFJTQAAAAAOAAAAOAAAAAYAAAAIAAAAAgAAAAAAAAAFAAAACAAAAAAAAAABAAAAAQAAAAAAAAAFAAQAAQAAAAEAAAAAAAAA</dataTransferInfos>
    <fcnCallPortGroups type="ModelRefInfoRepo.FcnCallPortGroup" uuid="42f9022a-efce-43bb-926b-82358dea7804">
      <hasDisableMethod>true</hasDisableMethod>
      <hasEnableMethod>true</hasEnableMethod>
      <hasTaskPriority>true</hasTaskPriority>
      <isAsync>true</isAsync>
      <isPeriodicFcnCall>true</isPeriodicFcnCall>
      <schedulingPriority>2147483647</schedulingPriority>
      <taskPriority>40</taskPriority>
      <tid>1</tid>
      <compDataInputPorts>1</compDataInputPorts>
      <compDataInputPorts>2</compDataInputPorts>
      <compDataInputPorts>3</compDataInputPorts>
      <compDataInputPorts>4</compDataInputPorts>
      <compDataInputPorts>5</compDataInputPorts>
      <compDataInputPorts>6</compDataInputPorts>
      <compDataInputPorts>7</compDataInputPorts>
      <compDataInputPorts>8</compDataInputPorts>
      <compDataInputPorts>9</compDataInputPorts>
      <compDataOutputPorts>0</compDataOutputPorts>
      <compDataOutputPorts>1</compDataOutputPorts>
      <compDataOutputPorts>2</compDataOutputPorts>
      <compDataOutputPorts>3</compDataOutputPorts>
      <compDataOutputPorts>4</compDataOutputPorts>
      <compDataOutputPorts>5</compDataOutputPorts>
      <compDataOutputPorts>6</compDataOutputPorts>
      <compDataOutputPorts>7</compDataOutputPorts>
      <compDataOutputPorts>8</compDataOutputPorts>
      <compDataOutputPorts>9</compDataOutputPorts>
      <compDataOutputPorts>10</compDataOutputPorts>
      <compDataOutputPorts>11</compDataOutputPorts>
      <dataInputPorts>1</dataInputPorts>
      <dataInputPorts>2</dataInputPorts>
      <dataInputPorts>3</dataInputPorts>
      <dataInputPorts>4</dataInputPorts>
      <dataInputPorts>5</dataInputPorts>
      <dataInputPorts>6</dataInputPorts>
      <dataInputPorts>7</dataInputPorts>
      <dataInputPorts>8</dataInputPorts>
      <dataInputPorts>9</dataInputPorts>
      <dataOutputPorts>0</dataOutputPorts>
      <dataOutputPorts>1</dataOutputPorts>
      <dataOutputPorts>2</dataOutputPorts>
      <dataOutputPorts>3</dataOutputPorts>
      <dataOutputPorts>4</dataOutputPorts>
      <dataOutputPorts>5</dataOutputPorts>
      <dataOutputPorts>6</dataOutputPorts>
      <dataOutputPorts>7</dataOutputPorts>
      <dataOutputPorts>8</dataOutputPorts>
      <dataOutputPorts>9</dataOutputPorts>
      <dataOutputPorts>10</dataOutputPorts>
      <dataOutputPorts>11</dataOutputPorts>
      <preCompRateSpec type="ModelRefInfoRepo.RateSpec" uuid="784cbc3d-5b05-4cd8-b584-3b53dd2fd8e1">
        <period>.01</period>
      </preCompRateSpec>
      <simulinkFunctionName type="ModelRefInfoRepo.QualifiedFunctionName" uuid="11ea1ba8-d822-422d-8a02-8f736791a985"/>
    </fcnCallPortGroups>
    <fundamentalSampleTimePeriod>.01</fundamentalSampleTimePeriod>
    <globalVariables>Boolean</globalVariables>
    <globalVariables>SInt16</globalVariables>
    <globalVariables>UInt8</globalVariables>
    <hasBlockWithPeriodicDiscreteSampleTime>true</hasBlockWithPeriodicDiscreteSampleTime>
    <hasBwsAccessed>true</hasBwsAccessed>
    <hasBwsAccessedByAnyModel>true</hasBwsAccessedByAnyModel>
    <hasNonVirtualConstantTs>true</hasNonVirtualConstantTs>
    <hasStatesModifiedInOutputUpdate>true</hasStatesModifiedInOutputUpdate>
    <inports type="ModelRefInfoRepo.InportInformation" uuid="b47dc766-843f-4f4f-ac95-f4048b345738">
      <hasSystemInitMethod>true</hasSystemInitMethod>
      <isFunctionCallInitiator>true</isFunctionCallInitiator>
      <isNotDerivPort>true</isNotDerivPort>
      <designMax>Inf</designMax>
      <designMin>-Inf</designMin>
      <indexType>2</indexType>
      <rateInfos type="ModelRefInfoRepo.RateInfo">
        <compiled>true</compiled>
        <period>.01</period>
        <priority>41</priority>
        <rateIdx>1</rateIdx>
        <taskedExplicitly>true</taskedExplicitly>
      </rateInfos>
      <resolvedSignalObject></resolvedSignalObject>
      <autosarInfo type="ModelRefInfoRepo.AUTOSARInportInfo" uuid="6bfa956f-ed58-4bf6-a487-19a2628b9992"/>
      <executionInterface type="ModelRefInfoRepo.InputExecutionInterface" uuid="56122840-2c3b-41ab-9bdd-5ac2abc8ef51"/>
      <sigNameToEMVCEMap type="ModelRefInfoRepo.SigNameEMVCEInfo" uuid="81727310-2b36-44c4-9af2-40418b8a2e4f"/>
    </inports>
    <inports type="ModelRefInfoRepo.InportInformation" uuid="0c99ce0c-2654-41c8-bf65-246254d88375">
      <isNotDerivPort>true</isNotDerivPort>
      <designMax>Inf</designMax>
      <designMin>-Inf</designMin>
      <indexType>2</indexType>
      <originalPortNumber>1</originalPortNumber>
      <rateInfos type="ModelRefInfoRepo.RateInfo">
        <compiled>true</compiled>
        <period>.01</period>
        <priority>41</priority>
        <rateIdx>1</rateIdx>
        <taskedExplicitly>true</taskedExplicitly>
      </rateInfos>
      <resolvedSignalObject></resolvedSignalObject>
      <autosarInfo type="ModelRefInfoRepo.AUTOSARInportInfo" uuid="ec47adf5-fd5a-4939-8b91-48f193aee9b9">
        <ElementName>VsINP_HWA_PassHandleHall_sig</ElementName>
        <PortName>VsINP_HWA_PassHandleHall_sig</PortName>
      </autosarInfo>
      <executionInterface type="ModelRefInfoRepo.InputExecutionInterface" uuid="dc159ce5-0b0c-4707-8763-e2a7c22daf09"/>
      <sigNameToEMVCEMap type="ModelRefInfoRepo.SigNameEMVCEInfo" uuid="ccd9c1ba-b665-4435-8112-85091e9e7a8f"/>
    </inports>
    <inports type="ModelRefInfoRepo.InportInformation" uuid="74636fee-1baa-4737-b10a-884d330d3f0a">
      <isNotDerivPort>true</isNotDerivPort>
      <designMax>Inf</designMax>
      <designMin>-Inf</designMin>
      <indexType>2</indexType>
      <originalPortNumber>2</originalPortNumber>
      <rateInfos type="ModelRefInfoRepo.RateInfo">
        <compiled>true</compiled>
        <period>.01</period>
        <priority>41</priority>
        <rateIdx>1</rateIdx>
        <taskedExplicitly>true</taskedExplicitly>
      </rateInfos>
      <resolvedSignalObject></resolvedSignalObject>
      <autosarInfo type="ModelRefInfoRepo.AUTOSARInportInfo" uuid="c9a4af51-1891-416e-aa98-d426099e5ebd">
        <ElementName>VsINP_HWA_RRHandleHall_sig</ElementName>
        <PortName>VsINP_HWA_RRHandleHall_sig</PortName>
      </autosarInfo>
      <executionInterface type="ModelRefInfoRepo.InputExecutionInterface" uuid="884c4076-1018-47df-8f22-6627f792a873"/>
      <sigNameToEMVCEMap type="ModelRefInfoRepo.SigNameEMVCEInfo" uuid="41583227-1113-4297-a986-f135f3a8b478"/>
    </inports>
    <inports type="ModelRefInfoRepo.InportInformation" uuid="a6651ae2-c1a3-426d-a9d7-b72831655463">
      <isNotDerivPort>true</isNotDerivPort>
      <designMax>Inf</designMax>
      <designMin>-Inf</designMin>
      <indexType>2</indexType>
      <originalPortNumber>3</originalPortNumber>
      <rateInfos type="ModelRefInfoRepo.RateInfo">
        <compiled>true</compiled>
        <period>.01</period>
        <priority>41</priority>
        <rateIdx>1</rateIdx>
        <taskedExplicitly>true</taskedExplicitly>
      </rateInfos>
      <resolvedSignalObject></resolvedSignalObject>
      <autosarInfo type="ModelRefInfoRepo.AUTOSARInportInfo" uuid="5dc1578a-cb12-4ebf-a909-a88ce181e3e6">
        <ElementName>VeINP_CAN_RDoorHandleReq_sig</ElementName>
        <PortName>VeINP_CAN_RDoorHandleReq_sig</PortName>
      </autosarInfo>
      <executionInterface type="ModelRefInfoRepo.InputExecutionInterface" uuid="92011088-396a-48ee-8ba2-f6b51372fc5f"/>
      <sigNameToEMVCEMap type="ModelRefInfoRepo.SigNameEMVCEInfo" uuid="d14bf2f2-3c22-4708-9be9-7af6308c871c"/>
    </inports>
    <inports type="ModelRefInfoRepo.InportInformation" uuid="ccb9cc37-5145-42a6-8b5b-a55f7a1264e1">
      <isNotDerivPort>true</isNotDerivPort>
      <designMax>Inf</designMax>
      <designMin>-Inf</designMin>
      <indexType>2</indexType>
      <originalPortNumber>4</originalPortNumber>
      <rateInfos type="ModelRefInfoRepo.RateInfo">
        <compiled>true</compiled>
        <period>.01</period>
        <priority>41</priority>
        <rateIdx>1</rateIdx>
        <taskedExplicitly>true</taskedExplicitly>
      </rateInfos>
      <resolvedSignalObject></resolvedSignalObject>
      <autosarInfo type="ModelRefInfoRepo.AUTOSARInportInfo" uuid="fa29ad72-e6a9-43f2-9e6b-ba760a7ec038">
        <ElementName>VeINP_CAN_RRDoorHandleReq_sig</ElementName>
        <PortName>VeINP_CAN_RRDoorHandleReq_sig</PortName>
      </autosarInfo>
      <executionInterface type="ModelRefInfoRepo.InputExecutionInterface" uuid="b5c355be-de0e-424b-bef0-0e73335c892f"/>
      <sigNameToEMVCEMap type="ModelRefInfoRepo.SigNameEMVCEInfo" uuid="8996d8eb-da58-403b-af14-93bb086d4bd2"/>
    </inports>
    <inports type="ModelRefInfoRepo.InportInformation" uuid="3e887bc6-16eb-47a0-9244-3391d6f4e433">
      <isNotDerivPort>true</isNotDerivPort>
      <designMax>Inf</designMax>
      <designMin>-Inf</designMin>
      <indexType>2</indexType>
      <originalPortNumber>5</originalPortNumber>
      <rateInfos type="ModelRefInfoRepo.RateInfo">
        <compiled>true</compiled>
        <period>.01</period>
        <priority>41</priority>
        <rateIdx>1</rateIdx>
        <taskedExplicitly>true</taskedExplicitly>
      </rateInfos>
      <resolvedSignalObject></resolvedSignalObject>
      <autosarInfo type="ModelRefInfoRepo.AUTOSARInportInfo" uuid="8e8d4463-c5a6-41ac-95c5-6d94d4b2034f">
        <ElementName>VsINP_EPRM_FRDoorHandleFromEE_sig</ElementName>
        <PortName>VsINP_EPRM_FRDoorHandleFromEE_sig</PortName>
      </autosarInfo>
      <executionInterface type="ModelRefInfoRepo.InputExecutionInterface" uuid="54e1f17a-c920-444b-9468-03ed2d626d34"/>
      <sigNameToEMVCEMap type="ModelRefInfoRepo.SigNameEMVCEInfo" uuid="59ece3d0-a277-4ce8-8fde-343d8a37c68e"/>
    </inports>
    <inports type="ModelRefInfoRepo.InportInformation" uuid="fdcdbe2c-24b9-4bd8-9c51-1033fd70c75c">
      <isNotDerivPort>true</isNotDerivPort>
      <designMax>Inf</designMax>
      <designMin>-Inf</designMin>
      <indexType>2</indexType>
      <originalPortNumber>6</originalPortNumber>
      <rateInfos type="ModelRefInfoRepo.RateInfo">
        <compiled>true</compiled>
        <period>.01</period>
        <priority>41</priority>
        <rateIdx>1</rateIdx>
        <taskedExplicitly>true</taskedExplicitly>
      </rateInfos>
      <resolvedSignalObject></resolvedSignalObject>
      <autosarInfo type="ModelRefInfoRepo.AUTOSARInportInfo" uuid="a1231f09-e849-4f22-8b08-213ac52d98a1">
        <ElementName>VsINP_EPRM_RRDoorHandleFromEE_sig</ElementName>
        <PortName>VsINP_EPRM_RRDoorHandleFromEE_sig</PortName>
      </autosarInfo>
      <executionInterface type="ModelRefInfoRepo.InputExecutionInterface" uuid="24b513e3-6f41-4e29-82cb-ad504d0683d2"/>
      <sigNameToEMVCEMap type="ModelRefInfoRepo.SigNameEMVCEInfo" uuid="17a1771a-8c24-4dd9-aa8d-86438d7ef003"/>
    </inports>
    <inports type="ModelRefInfoRepo.InportInformation" uuid="36fb0568-c469-46ce-a542-54b4303e79a0">
      <isNotDerivPort>true</isNotDerivPort>
      <designMax>Inf</designMax>
      <designMin>-Inf</designMin>
      <indexType>2</indexType>
      <originalPortNumber>7</originalPortNumber>
      <rateInfos type="ModelRefInfoRepo.RateInfo">
        <compiled>true</compiled>
        <period>.01</period>
        <priority>41</priority>
        <rateIdx>1</rateIdx>
        <taskedExplicitly>true</taskedExplicitly>
      </rateInfos>
      <resolvedSignalObject></resolvedSignalObject>
      <autosarInfo type="ModelRefInfoRepo.AUTOSARInportInfo" uuid="d4372da2-f802-42cf-a761-6ef9581829fe">
        <ElementName>VbINP_CAN_DoorHandleLrnReq_flg</ElementName>
        <PortName>VbINP_CAN_DoorHandleLrnReq_flg</PortName>
      </autosarInfo>
      <executionInterface type="ModelRefInfoRepo.InputExecutionInterface" uuid="3ebae6c0-6739-4961-b99f-b8652fc7e45f"/>
      <sigNameToEMVCEMap type="ModelRefInfoRepo.SigNameEMVCEInfo" uuid="bc15228d-aba0-46af-bc80-a122e55cbb7b"/>
    </inports>
    <inports type="ModelRefInfoRepo.InportInformation" uuid="243b2867-dcd5-41ae-85ac-ffa31d837b78">
      <isNotDerivPort>true</isNotDerivPort>
      <designMax>Inf</designMax>
      <designMin>-Inf</designMin>
      <indexType>2</indexType>
      <originalPortNumber>8</originalPortNumber>
      <rateInfos type="ModelRefInfoRepo.RateInfo">
        <compiled>true</compiled>
        <period>.01</period>
        <priority>41</priority>
        <rateIdx>1</rateIdx>
        <taskedExplicitly>true</taskedExplicitly>
      </rateInfos>
      <resolvedSignalObject></resolvedSignalObject>
      <autosarInfo type="ModelRefInfoRepo.AUTOSARInportInfo" uuid="06719856-de93-4e98-9ab7-b2b97234b48d">
        <ElementName>VeINP_EPRM_FRDoorHandleLrnStsFromEE_sig</ElementName>
        <PortName>VeINP_EPRM_FRDoorHandleLrnStsFromEE_sig</PortName>
      </autosarInfo>
      <executionInterface type="ModelRefInfoRepo.InputExecutionInterface" uuid="48745e24-bc1e-4080-bb70-fec13b566258"/>
      <sigNameToEMVCEMap type="ModelRefInfoRepo.SigNameEMVCEInfo" uuid="4f0721da-3650-40db-8eb8-9bbd1ed5833b"/>
    </inports>
    <inports type="ModelRefInfoRepo.InportInformation" uuid="f87bab1c-d2b3-49a1-8b53-670e9a42d049">
      <isNotDerivPort>true</isNotDerivPort>
      <designMax>Inf</designMax>
      <designMin>-Inf</designMin>
      <indexType>2</indexType>
      <originalPortNumber>9</originalPortNumber>
      <rateInfos type="ModelRefInfoRepo.RateInfo">
        <compiled>true</compiled>
        <period>.01</period>
        <priority>41</priority>
        <rateIdx>1</rateIdx>
        <taskedExplicitly>true</taskedExplicitly>
      </rateInfos>
      <resolvedSignalObject></resolvedSignalObject>
      <autosarInfo type="ModelRefInfoRepo.AUTOSARInportInfo" uuid="668da31e-1af7-4994-a7e2-1157672bc0bb">
        <ElementName>VeINP_EPRM_RRDoorHandleLrnStsFromEE_sig</ElementName>
        <PortName>VeINP_EPRM_RRDoorHandleLrnStsFromEE_sig</PortName>
      </autosarInfo>
      <executionInterface type="ModelRefInfoRepo.InputExecutionInterface" uuid="f5016b75-8697-4e38-9379-cbb50d82442f"/>
      <sigNameToEMVCEMap type="ModelRefInfoRepo.SigNameEMVCEInfo" uuid="b4f88d8b-122a-4f11-8892-4488ab3620a1"/>
    </inports>
    <isBdInSimModeForSimCodegenVariants>false</isBdInSimModeForSimCodegenVariants>
    <isInlineParamsOn>true</isInlineParamsOn>
    <isNumAllowedInstancesOne>true</isNumAllowedInstancesOne>
    <isOrigInportVirtualBus>false</isOrigInportVirtualBus>
    <isOrigInportVirtualBus>false</isOrigInportVirtualBus>
    <isOrigInportVirtualBus>false</isOrigInportVirtualBus>
    <isOrigInportVirtualBus>false</isOrigInportVirtualBus>
    <isOrigInportVirtualBus>false</isOrigInportVirtualBus>
    <isOrigInportVirtualBus>false</isOrigInportVirtualBus>
    <isOrigInportVirtualBus>false</isOrigInportVirtualBus>
    <isOrigInportVirtualBus>false</isOrigInportVirtualBus>
    <isOrigInportVirtualBus>false</isOrigInportVirtualBus>
    <isOrigInportVirtualBus>false</isOrigInportVirtualBus>
    <isOrigOutportVirtualBus>false</isOrigOutportVirtualBus>
    <isOrigOutportVirtualBus>false</isOrigOutportVirtualBus>
    <isOrigOutportVirtualBus>false</isOrigOutportVirtualBus>
    <isOrigOutportVirtualBus>false</isOrigOutportVirtualBus>
    <isOrigOutportVirtualBus>false</isOrigOutportVirtualBus>
    <isOrigOutportVirtualBus>false</isOrigOutportVirtualBus>
    <isOrigOutportVirtualBus>false</isOrigOutportVirtualBus>
    <isOrigOutportVirtualBus>false</isOrigOutportVirtualBus>
    <isOrigOutportVirtualBus>false</isOrigOutportVirtualBus>
    <isOrigOutportVirtualBus>false</isOrigOutportVirtualBus>
    <isOrigOutportVirtualBus>false</isOrigOutportVirtualBus>
    <isOrigOutportVirtualBus>false</isOrigOutportVirtualBus>
    <loggingSaveFormat>6</loggingSaveFormat>
    <maxFreqHz>-1.0</maxFreqHz>
    <numDStateRecs>8</numDStateRecs>
    <numDataInputPorts>10</numDataInputPorts>
    <numInportFcnCallPortGroups>1</numInportFcnCallPortGroups>
    <numLoggableDStateRecs>8</numLoggableDStateRecs>
    <numLoggableJacobianDStates>0</numLoggableJacobianDStates>
    <origInportBusType></origInportBusType>
    <origInportBusType></origInportBusType>
    <origInportBusType></origInportBusType>
    <origInportBusType></origInportBusType>
    <origInportBusType></origInportBusType>
    <origInportBusType></origInportBusType>
    <origInportBusType></origInportBusType>
    <origInportBusType></origInportBusType>
    <origInportBusType></origInportBusType>
    <origInportBusType></origInportBusType>
    <origOutportBusOutputAsStruct>false</origOutportBusOutputAsStruct>
    <origOutportBusOutputAsStruct>false</origOutportBusOutputAsStruct>
    <origOutportBusOutputAsStruct>false</origOutportBusOutputAsStruct>
    <origOutportBusOutputAsStruct>false</origOutportBusOutputAsStruct>
    <origOutportBusOutputAsStruct>false</origOutportBusOutputAsStruct>
    <origOutportBusOutputAsStruct>false</origOutportBusOutputAsStruct>
    <origOutportBusOutputAsStruct>false</origOutportBusOutputAsStruct>
    <origOutportBusOutputAsStruct>false</origOutportBusOutputAsStruct>
    <origOutportBusOutputAsStruct>false</origOutportBusOutputAsStruct>
    <origOutportBusOutputAsStruct>false</origOutportBusOutputAsStruct>
    <origOutportBusOutputAsStruct>false</origOutportBusOutputAsStruct>
    <origOutportBusOutputAsStruct>false</origOutportBusOutputAsStruct>
    <origOutportBusType></origOutportBusType>
    <origOutportBusType></origOutportBusType>
    <origOutportBusType></origOutportBusType>
    <origOutportBusType></origOutportBusType>
    <origOutportBusType></origOutportBusType>
    <origOutportBusType></origOutportBusType>
    <origOutportBusType></origOutportBusType>
    <origOutportBusType></origOutportBusType>
    <origOutportBusType></origOutportBusType>
    <origOutportBusType></origOutportBusType>
    <origOutportBusType></origOutportBusType>
    <origOutportBusType></origOutportBusType>
    <outports type="ModelRefInfoRepo.OutportInformation" uuid="6d87b7de-e8ae-4d72-b579-385fedefac40">
      <hasSystemInitMethod>true</hasSystemInitMethod>
      <isInitializedWithIC>true</isInitializedWithIC>
      <designMax>Inf</designMax>
      <designMin>-Inf</designMin>
      <rateInfos type="ModelRefInfoRepo.RateInfo">
        <compiled>true</compiled>
        <period>.01</period>
        <priority>41</priority>
        <rateIdx>1</rateIdx>
        <taskedExplicitly>true</taskedExplicitly>
      </rateInfos>
      <resolvedSignalObject></resolvedSignalObject>
      <autosarInfo type="ModelRefInfoRepo.AUTOSAROutportInfo" uuid="f9afc25a-476b-4d63-80ae-853ad8acf5e0">
        <ElementName>VeOUT_DHM_FRDoorHandleSts_sig</ElementName>
        <PortName>VeOUT_DHM_FRDoorHandleSts_sig</PortName>
      </autosarInfo>
      <executionInterface type="ModelRefInfoRepo.OutputExecutionInterface" uuid="5e89506e-eb13-4130-bb03-b6444d7bf766"/>
      <sigNameToEMVCEMap type="ModelRefInfoRepo.SigNameEMVCEInfo" uuid="ae0431c3-c28c-400a-8839-c681110bf43a"/>
    </outports>
    <outports type="ModelRefInfoRepo.OutportInformation" uuid="4643811a-8ecc-43cd-a0ab-e8b6a3334640">
      <hasSystemInitMethod>true</hasSystemInitMethod>
      <isInitializedWithIC>true</isInitializedWithIC>
      <designMax>Inf</designMax>
      <designMin>-Inf</designMin>
      <originalPortNumber>1</originalPortNumber>
      <rateInfos type="ModelRefInfoRepo.RateInfo">
        <compiled>true</compiled>
        <period>.01</period>
        <priority>41</priority>
        <rateIdx>1</rateIdx>
        <taskedExplicitly>true</taskedExplicitly>
      </rateInfos>
      <resolvedSignalObject></resolvedSignalObject>
      <autosarInfo type="ModelRefInfoRepo.AUTOSAROutportInfo" uuid="e2c935b3-91e8-4dbb-91b6-d0dc7988e9a1">
        <ElementName>VeOUT_DHM_RRDoorHandleSts_sig</ElementName>
        <PortName>VeOUT_DHM_RRDoorHandleSts_sig</PortName>
      </autosarInfo>
      <executionInterface type="ModelRefInfoRepo.OutputExecutionInterface" uuid="4a72f7a5-30bd-4bcd-9f03-3f0ea01e7226"/>
      <sigNameToEMVCEMap type="ModelRefInfoRepo.SigNameEMVCEInfo" uuid="e409333b-e0cf-4cce-8eaa-07836ad2d5c3"/>
    </outports>
    <outports type="ModelRefInfoRepo.OutportInformation" uuid="53569324-49ed-4204-966d-5ac52d6983d3">
      <drivenByOutputPortWithCGInit>true</drivenByOutputPortWithCGInit>
      <hasSystemInitMethod>true</hasSystemInitMethod>
      <isInitializedWithIC>true</isInitializedWithIC>
      <designMax>Inf</designMax>
      <designMin>-Inf</designMin>
      <originalPortNumber>2</originalPortNumber>
      <rateInfos type="ModelRefInfoRepo.RateInfo">
        <compiled>true</compiled>
        <period>.01</period>
        <priority>41</priority>
        <rateIdx>1</rateIdx>
        <taskedExplicitly>true</taskedExplicitly>
      </rateInfos>
      <resolvedSignalObject></resolvedSignalObject>
      <autosarInfo type="ModelRefInfoRepo.AUTOSAROutportInfo" uuid="766ac670-50c5-4138-95cb-026c8103d2a4">
        <ElementName>VbOUT_DHM_FRHadUnfold_flg</ElementName>
        <PortName>VbOUT_DHM_FRHadUnfold_flg</PortName>
      </autosarInfo>
      <executionInterface type="ModelRefInfoRepo.OutputExecutionInterface" uuid="605cf697-e37d-46cc-92d4-158394f49615"/>
      <sigNameToEMVCEMap type="ModelRefInfoRepo.SigNameEMVCEInfo" uuid="ef54c989-e09b-42b5-91c2-9bd4494bd6ce"/>
    </outports>
    <outports type="ModelRefInfoRepo.OutportInformation" uuid="4898cde1-6af3-4ee2-adc4-2321f6d20853">
      <drivenByOutputPortWithCGInit>true</drivenByOutputPortWithCGInit>
      <hasSystemInitMethod>true</hasSystemInitMethod>
      <isInitializedWithIC>true</isInitializedWithIC>
      <designMax>Inf</designMax>
      <designMin>-Inf</designMin>
      <originalPortNumber>3</originalPortNumber>
      <rateInfos type="ModelRefInfoRepo.RateInfo">
        <compiled>true</compiled>
        <period>.01</period>
        <priority>41</priority>
        <rateIdx>1</rateIdx>
        <taskedExplicitly>true</taskedExplicitly>
      </rateInfos>
      <resolvedSignalObject></resolvedSignalObject>
      <autosarInfo type="ModelRefInfoRepo.AUTOSAROutportInfo" uuid="4550faeb-9d1a-4f08-907c-eee5ef4404fa">
        <ElementName>VbOUT_DHM_FRHadFold_flg</ElementName>
        <PortName>VbOUT_DHM_FRHadFold_flg</PortName>
      </autosarInfo>
      <executionInterface type="ModelRefInfoRepo.OutputExecutionInterface" uuid="5368df66-8648-4b11-9b06-4b35fa16e897"/>
      <sigNameToEMVCEMap type="ModelRefInfoRepo.SigNameEMVCEInfo" uuid="29836ef7-5156-4371-886b-d7ca6a6a8b2e"/>
    </outports>
    <outports type="ModelRefInfoRepo.OutportInformation" uuid="d34c2a8b-6080-4965-a550-b9bf32c16f66">
      <drivenByOutputPortWithCGInit>true</drivenByOutputPortWithCGInit>
      <hasSystemInitMethod>true</hasSystemInitMethod>
      <isInitializedWithIC>true</isInitializedWithIC>
      <designMax>Inf</designMax>
      <designMin>-Inf</designMin>
      <originalPortNumber>4</originalPortNumber>
      <rateInfos type="ModelRefInfoRepo.RateInfo">
        <compiled>true</compiled>
        <period>.01</period>
        <priority>41</priority>
        <rateIdx>1</rateIdx>
        <taskedExplicitly>true</taskedExplicitly>
      </rateInfos>
      <resolvedSignalObject></resolvedSignalObject>
      <autosarInfo type="ModelRefInfoRepo.AUTOSAROutportInfo" uuid="1616e4f7-65f5-42bd-af68-e390d45270e9">
        <ElementName>VbOUT_DHM_RRHandleUnfold_flg</ElementName>
        <PortName>VbOUT_DHM_RRHandleUnfold_flg</PortName>
      </autosarInfo>
      <executionInterface type="ModelRefInfoRepo.OutputExecutionInterface" uuid="ef53fee3-b82d-4563-b90d-9250c7fb1c7b"/>
      <sigNameToEMVCEMap type="ModelRefInfoRepo.SigNameEMVCEInfo" uuid="f305fdcd-09a2-4743-9a09-bc41ba1c9340"/>
    </outports>
    <outports type="ModelRefInfoRepo.OutportInformation" uuid="7dc4157b-ed3d-4f7c-a7d9-556345cc1402">
      <drivenByOutputPortWithCGInit>true</drivenByOutputPortWithCGInit>
      <hasSystemInitMethod>true</hasSystemInitMethod>
      <isInitializedWithIC>true</isInitializedWithIC>
      <designMax>Inf</designMax>
      <designMin>-Inf</designMin>
      <originalPortNumber>5</originalPortNumber>
      <rateInfos type="ModelRefInfoRepo.RateInfo">
        <compiled>true</compiled>
        <period>.01</period>
        <priority>41</priority>
        <rateIdx>1</rateIdx>
        <taskedExplicitly>true</taskedExplicitly>
      </rateInfos>
      <resolvedSignalObject></resolvedSignalObject>
      <autosarInfo type="ModelRefInfoRepo.AUTOSAROutportInfo" uuid="9f3a71bc-d36b-4a0e-86e4-2fec169afb4a">
        <ElementName>VbOUT_DHM_RRHandleFold_flg</ElementName>
        <PortName>VbOUT_DHM_RRHandleFold_flg</PortName>
      </autosarInfo>
      <executionInterface type="ModelRefInfoRepo.OutputExecutionInterface" uuid="3f81272b-8373-4245-8555-5dca0cdfe2bc"/>
      <sigNameToEMVCEMap type="ModelRefInfoRepo.SigNameEMVCEInfo" uuid="48a3a090-e68e-49e8-838a-37abf37e51a9"/>
    </outports>
    <outports type="ModelRefInfoRepo.OutportInformation" uuid="4620189a-a75a-4bdd-9d10-a793304103dc">
      <drivenByOutputPortWithCGInit>true</drivenByOutputPortWithCGInit>
      <hasSystemInitMethod>true</hasSystemInitMethod>
      <isInitializedWithIC>true</isInitializedWithIC>
      <designMax>Inf</designMax>
      <designMin>-Inf</designMin>
      <originalPortNumber>6</originalPortNumber>
      <rateInfos type="ModelRefInfoRepo.RateInfo">
        <compiled>true</compiled>
        <period>.01</period>
        <priority>41</priority>
        <rateIdx>1</rateIdx>
        <taskedExplicitly>true</taskedExplicitly>
      </rateInfos>
      <resolvedSignalObject></resolvedSignalObject>
      <autosarInfo type="ModelRefInfoRepo.AUTOSAROutportInfo" uuid="9c929b09-4fdb-4a71-978f-8c9b91ba143b">
        <ElementName>VsINP_DHM_FRDoorHandleToEE_sig</ElementName>
        <PortName>VsINP_DHM_FRDoorHandleToEE_sig</PortName>
      </autosarInfo>
      <executionInterface type="ModelRefInfoRepo.OutputExecutionInterface" uuid="dfdb1392-7e93-41a6-b583-81cc26a20586"/>
      <sigNameToEMVCEMap type="ModelRefInfoRepo.SigNameEMVCEInfo" uuid="ce942ef0-6411-41c4-bd2d-07ec55b92e89"/>
    </outports>
    <outports type="ModelRefInfoRepo.OutportInformation" uuid="8f8ebc0e-87c4-428c-9a33-3005f6882bd0">
      <drivenByOutputPortWithCGInit>true</drivenByOutputPortWithCGInit>
      <hasSystemInitMethod>true</hasSystemInitMethod>
      <isInitializedWithIC>true</isInitializedWithIC>
      <designMax>Inf</designMax>
      <designMin>-Inf</designMin>
      <originalPortNumber>7</originalPortNumber>
      <rateInfos type="ModelRefInfoRepo.RateInfo">
        <compiled>true</compiled>
        <period>.01</period>
        <priority>41</priority>
        <rateIdx>1</rateIdx>
        <taskedExplicitly>true</taskedExplicitly>
      </rateInfos>
      <resolvedSignalObject></resolvedSignalObject>
      <autosarInfo type="ModelRefInfoRepo.AUTOSAROutportInfo" uuid="7d69e9d9-9c01-4229-92e3-9019ad6d9f83">
        <ElementName>VsINP_DHM_RRDoorHandleToEE_sig</ElementName>
        <PortName>VsINP_DHM_RRDoorHandleToEE_sig</PortName>
      </autosarInfo>
      <executionInterface type="ModelRefInfoRepo.OutputExecutionInterface" uuid="fd2b8b13-3c96-4f92-8d34-a734b8c7b4bb"/>
      <sigNameToEMVCEMap type="ModelRefInfoRepo.SigNameEMVCEInfo" uuid="18b4df9e-af3c-4fc3-bfc7-6aeaacff7454"/>
    </outports>
    <outports type="ModelRefInfoRepo.OutportInformation" uuid="dd542299-3ab5-4a74-a2a7-7a1db9a8dfc0">
      <hasSystemInitMethod>true</hasSystemInitMethod>
      <isInitializedWithIC>true</isInitializedWithIC>
      <designMax>Inf</designMax>
      <designMin>-Inf</designMin>
      <originalPortNumber>8</originalPortNumber>
      <rateInfos type="ModelRefInfoRepo.RateInfo">
        <compiled>true</compiled>
        <period>.01</period>
        <priority>41</priority>
        <rateIdx>1</rateIdx>
        <taskedExplicitly>true</taskedExplicitly>
      </rateInfos>
      <resolvedSignalObject></resolvedSignalObject>
      <autosarInfo type="ModelRefInfoRepo.AUTOSAROutportInfo" uuid="ba0d47c1-f127-4551-946d-a0e40aeb81ff">
        <ElementName>VeINP_DHM_FRDoorHandleLrnSts_sig</ElementName>
        <PortName>VeINP_DHM_FRDoorHandleLrnSts_sig</PortName>
      </autosarInfo>
      <executionInterface type="ModelRefInfoRepo.OutputExecutionInterface" uuid="0b44ce96-0fc5-4df7-aa2d-2f9fc58a383b"/>
      <sigNameToEMVCEMap type="ModelRefInfoRepo.SigNameEMVCEInfo" uuid="2a7c26d0-28bb-446b-b823-8c7bb813c296"/>
    </outports>
    <outports type="ModelRefInfoRepo.OutportInformation" uuid="291567bd-9904-436d-b179-598c2aefdf60">
      <hasSystemInitMethod>true</hasSystemInitMethod>
      <isInitializedWithIC>true</isInitializedWithIC>
      <designMax>Inf</designMax>
      <designMin>-Inf</designMin>
      <originalPortNumber>9</originalPortNumber>
      <rateInfos type="ModelRefInfoRepo.RateInfo">
        <compiled>true</compiled>
        <period>.01</period>
        <priority>41</priority>
        <rateIdx>1</rateIdx>
        <taskedExplicitly>true</taskedExplicitly>
      </rateInfos>
      <resolvedSignalObject></resolvedSignalObject>
      <autosarInfo type="ModelRefInfoRepo.AUTOSAROutportInfo" uuid="6d66494e-7a28-446f-b937-8009c28446d4">
        <ElementName>VeINP_DHM_RRDoorHandleLrnSts_sig</ElementName>
        <PortName>VeINP_DHM_RRDoorHandleLrnSts_sig</PortName>
      </autosarInfo>
      <executionInterface type="ModelRefInfoRepo.OutputExecutionInterface" uuid="82d43f9e-1ac9-4421-998a-48cf279f6c57"/>
      <sigNameToEMVCEMap type="ModelRefInfoRepo.SigNameEMVCEInfo" uuid="c5637ba9-5810-496f-bd8e-0d4b63a4f232"/>
    </outports>
    <outports type="ModelRefInfoRepo.OutportInformation" uuid="f788b249-49b8-4318-82df-3d9d98c4ec44">
      <drivenByOutputPortWithCGInit>true</drivenByOutputPortWithCGInit>
      <hasSystemInitMethod>true</hasSystemInitMethod>
      <isInitializedWithIC>true</isInitializedWithIC>
      <designMax>Inf</designMax>
      <designMin>-Inf</designMin>
      <originalPortNumber>10</originalPortNumber>
      <rateInfos type="ModelRefInfoRepo.RateInfo">
        <compiled>true</compiled>
        <period>.01</period>
        <priority>41</priority>
        <rateIdx>1</rateIdx>
        <taskedExplicitly>true</taskedExplicitly>
      </rateInfos>
      <resolvedSignalObject></resolvedSignalObject>
      <autosarInfo type="ModelRefInfoRepo.AUTOSAROutportInfo" uuid="89542501-1c37-4f97-a334-d02f4b0ee487">
        <ElementName>VeOUT_DHM_FRDoorHandleLrnStsEE_sig</ElementName>
        <PortName>VeOUT_DHM_FRDoorHandleLrnStsEE_sig</PortName>
      </autosarInfo>
      <executionInterface type="ModelRefInfoRepo.OutputExecutionInterface" uuid="9d690d50-db6b-49bd-990c-45792a1c0189"/>
      <sigNameToEMVCEMap type="ModelRefInfoRepo.SigNameEMVCEInfo" uuid="97732a1f-f805-4c08-8f82-a7fe4c471732"/>
    </outports>
    <outports type="ModelRefInfoRepo.OutportInformation" uuid="bf49e1b4-edbc-4ba6-ac80-eaa83becc7fd">
      <drivenByOutputPortWithCGInit>true</drivenByOutputPortWithCGInit>
      <hasSystemInitMethod>true</hasSystemInitMethod>
      <isInitializedWithIC>true</isInitializedWithIC>
      <designMax>Inf</designMax>
      <designMin>-Inf</designMin>
      <originalPortNumber>11</originalPortNumber>
      <rateInfos type="ModelRefInfoRepo.RateInfo">
        <compiled>true</compiled>
        <period>.01</period>
        <priority>41</priority>
        <rateIdx>1</rateIdx>
        <taskedExplicitly>true</taskedExplicitly>
      </rateInfos>
      <resolvedSignalObject></resolvedSignalObject>
      <autosarInfo type="ModelRefInfoRepo.AUTOSAROutportInfo" uuid="df7cf6c4-2897-4104-89b2-e7e4eb2e306b">
        <ElementName>VeOUT_DHM_RRDoorHandleLrnStsEE_sig</ElementName>
        <PortName>VeOUT_DHM_RRDoorHandleLrnStsEE_sig</PortName>
      </autosarInfo>
      <executionInterface type="ModelRefInfoRepo.OutputExecutionInterface" uuid="73329b50-6830-4d65-8940-4881bacb8686"/>
      <sigNameToEMVCEMap type="ModelRefInfoRepo.SigNameEMVCEInfo" uuid="3a4c7eab-2922-4230-861d-7734dbf12ce4"/>
    </outports>
    <removeResetFunc>true</removeResetFunc>
    <runtimeNonFcnCallRateInfos type="ModelRefInfoRepo.RateInfo">
      <compiled>true</compiled>
      <isEmpty>true</isEmpty>
      <period>.01</period>
      <priority>40</priority>
      <rateIdx>0</rateIdx>
    </runtimeNonFcnCallRateInfos>
    <runtimeNonFcnCallRateInfos type="ModelRefInfoRepo.RateInfo">
      <compiled>true</compiled>
      <period>.01</period>
      <priority>41</priority>
      <rateIdx>1</rateIdx>
      <taskedExplicitly>true</taskedExplicitly>
    </runtimeNonFcnCallRateInfos>
    <sampleTimeInheritanceRule>2</sampleTimeInheritanceRule>
    <solverStatusFlags>323</solverStatusFlags>
    <standaloneEnumInfos type="ModelRefInfoRepo.StandaloneEnumInfo" uuid="3451141c-38df-49a2-9bfa-2cca988c1c16">
      <defaultValue>Learn_Invalid</defaultValue>
      <enumName>Learn_Sts_E</enumName>
      <labels>Learn_Invalid</labels>
      <labels>Learn_Success</labels>
      <labels>Learn_Fail</labels>
      <labels>Learn_Reserved</labels>
      <storageType>uint8</storageType>
      <values>0</values>
      <values>1</values>
      <values>2</values>
      <values>3</values>
    </standaloneEnumInfos>
    <standaloneEnumInfos type="ModelRefInfoRepo.StandaloneEnumInfo" uuid="4c0d2978-05b3-488e-af4e-a0cebc9ad902">
      <defaultValue>Hnd_Fold</defaultValue>
      <enumName>HndPos_Sts_E</enumName>
      <labels>Hnd_Fold</labels>
      <labels>Hnd_Unfold</labels>
      <labels>Hnd_Unknown</labels>
      <labels>Hnd_Reserved</labels>
      <storageType>uint8</storageType>
      <values>0</values>
      <values>1</values>
      <values>2</values>
      <values>3</values>
    </standaloneEnumInfos>
    <timingAndTaskingRegistry>&lt;?xml version=&quot;1.0&quot;?&gt;
&lt;slexec_sto version=&quot;1.1&quot; packageUris=&quot;http://schema.mathworks.com/mf0/slexec_mm_sto/R2022a_202107291127&quot;&gt;
  &lt;sto.Registry type=&quot;sto.Registry&quot; uuid=&quot;d9b2e455-7f97-45f8-a70e-92783f1f8494&quot;&gt;
    &lt;clocks type=&quot;sto.Timer&quot; uuid=&quot;5911e7ff-5fc3-4d58-9465-202d48e04f07&quot;&gt;
      &lt;computedFundamentalDiscretePeriod&gt;.01&lt;/computedFundamentalDiscretePeriod&gt;
      &lt;resolution&gt;.01&lt;/resolution&gt;
      &lt;clockTickConstraint&gt;PeriodicWithFixedResolution&lt;/clockTickConstraint&gt;
      &lt;rates type=&quot;sto.ClassicPeriodicDiscreteRate&quot; uuid=&quot;5032ea4b-f137-4444-93c0-c6a6533157c7&quot;&gt;
        &lt;annotation&gt;D1&lt;/annotation&gt;
        &lt;colorIndex&gt;2&lt;/colorIndex&gt;
        &lt;description&gt;离散 1&lt;/description&gt;
        &lt;taskId&gt;_task0&lt;/taskId&gt;
        &lt;rateSpec type=&quot;sto.RateSpec&quot; uuid=&quot;2fad9b11-5ef0-401c-94bb-728187d6af25&quot;&gt;
          &lt;period&gt;.01&lt;/period&gt;
          &lt;rateType&gt;ClassicPeriodicDiscrete&lt;/rateType&gt;
        &lt;/rateSpec&gt;
      &lt;/rates&gt;
      &lt;rates type=&quot;sto.ClassicPeriodicDiscreteRate&quot; uuid=&quot;f372ef00-3268-45ff-af5a-2c274963af8b&quot;&gt;
        &lt;annotation&gt;F0&lt;/annotation&gt;
        &lt;colorIndex&gt;2&lt;/colorIndex&gt;
        &lt;description&gt;导出的离散&lt;/description&gt;
        &lt;rateIdx&gt;1&lt;/rateIdx&gt;
        &lt;taskId&gt;DHM_Step&lt;/taskId&gt;
        &lt;rateSpec type=&quot;sto.RateSpec&quot; uuid=&quot;db350b7c-6b06-4bcd-b098-d10de65d6f67&quot;&gt;
          &lt;period&gt;.01&lt;/period&gt;
          &lt;rateType&gt;ClassicPeriodicDiscrete&lt;/rateType&gt;
        &lt;/rateSpec&gt;
      &lt;/rates&gt;
      &lt;timeAdvanceMode&gt;FixedStep&lt;/timeAdvanceMode&gt;
      &lt;baseRate type=&quot;sto.ClassicPeriodicDiscreteRate&quot; uuid=&quot;bc17bb0b-1c97-4c50-8cfe-2926d04b68c3&quot;&gt;
        &lt;annotation&gt;D1&lt;/annotation&gt;
        &lt;colorIndex&gt;2&lt;/colorIndex&gt;
        &lt;description&gt;离散 1&lt;/description&gt;
        &lt;taskId&gt;_task0&lt;/taskId&gt;
        &lt;rateSpec type=&quot;sto.RateSpec&quot; uuid=&quot;0b3e9466-9540-43a7-89b1-598c9c6711fa&quot;&gt;
          &lt;period&gt;.01&lt;/period&gt;
          &lt;rateType&gt;ClassicPeriodicDiscrete&lt;/rateType&gt;
        &lt;/rateSpec&gt;
      &lt;/baseRate&gt;
    &lt;/clocks&gt;
    &lt;clocks type=&quot;sto.Event&quot; uuid=&quot;46b80698-f539-472a-bba6-82e3c5366faf&quot;&gt;
      &lt;eventType&gt;POWER_UP_EVENT&lt;/eventType&gt;
      &lt;cNum&gt;1&lt;/cNum&gt;
      &lt;clockType&gt;Event&lt;/clockType&gt;
      &lt;identifier&gt;Init&lt;/identifier&gt;
      &lt;rates type=&quot;sto.ModelWideEventRate&quot; uuid=&quot;804c09fb-b49e-4914-bd3f-579ff1c0f139&quot;&gt;
        &lt;annotation&gt;Init&lt;/annotation&gt;
        &lt;clockId&gt;Init&lt;/clockId&gt;
        &lt;colorIndex&gt;10&lt;/colorIndex&gt;
        &lt;description&gt;初始化&lt;/description&gt;
        &lt;rateIdx&gt;2&lt;/rateIdx&gt;
        &lt;taskId&gt;ModelWideInitializeEvent&lt;/taskId&gt;
        &lt;rateSpec type=&quot;sto.RateSpec&quot; uuid=&quot;ce014f9b-5f9d-4d79-ab13-62e03edaa4e8&quot;&gt;
          &lt;offset&gt;1.0&lt;/offset&gt;
          &lt;period&gt;Inf&lt;/period&gt;
          &lt;rateType&gt;ModelWideInitializeEvent&lt;/rateType&gt;
        &lt;/rateSpec&gt;
      &lt;/rates&gt;
      &lt;taskingMode&gt;ExplicitTasking&lt;/taskingMode&gt;
      &lt;timeAdvanceMode&gt;None&lt;/timeAdvanceMode&gt;
    &lt;/clocks&gt;
    &lt;clocks type=&quot;sto.Event&quot; uuid=&quot;ad559ff3-9a0c-4629-8eb1-88775188816e&quot;&gt;
      &lt;eventType&gt;PARAMETER_CHANGE_EVENT&lt;/eventType&gt;
      &lt;cNum&gt;2&lt;/cNum&gt;
      &lt;clockType&gt;Event&lt;/clockType&gt;
      &lt;identifier&gt;ParameterChangeEvent&lt;/identifier&gt;
      &lt;rates type=&quot;sto.ModelWideEventRate&quot; uuid=&quot;1f6d8ed4-664f-454e-acfc-a98f8cc124ae&quot;&gt;
        &lt;clockId&gt;ParameterChangeEvent&lt;/clockId&gt;
        &lt;rateIdx&gt;-1&lt;/rateIdx&gt;
        &lt;taskId&gt;ModelWideParameterChangeEvent&lt;/taskId&gt;
        &lt;useForExecution&gt;NotForExecution&lt;/useForExecution&gt;
        &lt;rateSpec type=&quot;sto.RateSpec&quot; uuid=&quot;a5d10f3a-0c84-4825-a9fd-e4134ce9509e&quot;&gt;
          &lt;period&gt;Inf&lt;/period&gt;
          &lt;rateType&gt;ModelWideParameterChangeEvent&lt;/rateType&gt;
        &lt;/rateSpec&gt;
      &lt;/rates&gt;
      &lt;taskingMode&gt;ExplicitTasking&lt;/taskingMode&gt;
      &lt;timeAdvanceMode&gt;None&lt;/timeAdvanceMode&gt;
    &lt;/clocks&gt;
    &lt;executionSpec&gt;Undetermined&lt;/executionSpec&gt;
    &lt;taskPriorityDirection&gt;HighNumberLast&lt;/taskPriorityDirection&gt;
    &lt;timeAdvanceMode&gt;FixedStep&lt;/timeAdvanceMode&gt;
    &lt;taskRegistry type=&quot;sto.TaskRegistry&quot; uuid=&quot;ea75f7e3-4c26-430a-9490-16097fbece02&quot;&gt;
      &lt;rootTaskHierarchyElements type=&quot;sto.Task&quot; uuid=&quot;37aadcf8-2a51-46f4-b8de-aa27aa928c67&quot;&gt;
        &lt;isExecutable&gt;true&lt;/isExecutable&gt;
        &lt;rates type=&quot;sto.ClassicPeriodicDiscreteRate&quot; uuid=&quot;5a697e70-9f30-4978-a62f-28de37a42b5f&quot;&gt;
          &lt;annotation&gt;D1&lt;/annotation&gt;
          &lt;colorIndex&gt;2&lt;/colorIndex&gt;
          &lt;description&gt;离散 1&lt;/description&gt;
          &lt;taskId&gt;_task0&lt;/taskId&gt;
          &lt;rateSpec type=&quot;sto.RateSpec&quot; uuid=&quot;476b00b1-0b19-41d0-addd-da0516d6096b&quot;&gt;
            &lt;period&gt;.01&lt;/period&gt;
            &lt;rateType&gt;ClassicPeriodicDiscrete&lt;/rateType&gt;
          &lt;/rateSpec&gt;
        &lt;/rates&gt;
        &lt;elementType&gt;Task&lt;/elementType&gt;
        &lt;identifier&gt;_task0&lt;/identifier&gt;
        &lt;priority&gt;40&lt;/priority&gt;
      &lt;/rootTaskHierarchyElements&gt;
      &lt;rootTaskHierarchyElements type=&quot;sto.Task&quot; uuid=&quot;17afd754-d9ad-4a6a-9ef1-d054230c3e91&quot;&gt;
        &lt;isExecutable&gt;true&lt;/isExecutable&gt;
        &lt;isExplicit&gt;true&lt;/isExplicit&gt;
        &lt;rates type=&quot;sto.ClassicPeriodicDiscreteRate&quot; uuid=&quot;f97335eb-dbe9-4f75-a42e-cc72aa1768aa&quot;&gt;
          &lt;annotation&gt;F0&lt;/annotation&gt;
          &lt;colorIndex&gt;2&lt;/colorIndex&gt;
          &lt;description&gt;导出的离散&lt;/description&gt;
          &lt;rateIdx&gt;1&lt;/rateIdx&gt;
          &lt;taskId&gt;DHM_Step&lt;/taskId&gt;
          &lt;rateSpec type=&quot;sto.RateSpec&quot; uuid=&quot;8ed98200-1082-4f93-a4a3-db146a0937af&quot;&gt;
            &lt;period&gt;.01&lt;/period&gt;
            &lt;rateType&gt;ClassicPeriodicDiscrete&lt;/rateType&gt;
          &lt;/rateSpec&gt;
        &lt;/rates&gt;
        &lt;tNum&gt;1&lt;/tNum&gt;
        &lt;elementType&gt;Task&lt;/elementType&gt;
        &lt;identifier&gt;DHM_Step&lt;/identifier&gt;
        &lt;priority&gt;41&lt;/priority&gt;
      &lt;/rootTaskHierarchyElements&gt;
      &lt;rootTaskHierarchyElements type=&quot;sto.Task&quot; uuid=&quot;c9f46d26-f902-4aba-a729-9f2ed22f0516&quot;&gt;
        &lt;isExplicit&gt;true&lt;/isExplicit&gt;
        &lt;rates type=&quot;sto.ModelWideEventRate&quot; uuid=&quot;25830a61-d863-4c14-a13a-93643dc09633&quot;&gt;
          &lt;clockId&gt;ParameterChangeEvent&lt;/clockId&gt;
          &lt;rateIdx&gt;-1&lt;/rateIdx&gt;
          &lt;taskId&gt;ModelWideParameterChangeEvent&lt;/taskId&gt;
          &lt;useForExecution&gt;NotForExecution&lt;/useForExecution&gt;
          &lt;rateSpec type=&quot;sto.RateSpec&quot; uuid=&quot;9b94e9d6-ae08-4ba0-a1fa-f226a7130d25&quot;&gt;
            &lt;period&gt;Inf&lt;/period&gt;
            &lt;rateType&gt;ModelWideParameterChangeEvent&lt;/rateType&gt;
          &lt;/rateSpec&gt;
        &lt;/rates&gt;
        &lt;elementType&gt;Task&lt;/elementType&gt;
        &lt;identifier&gt;ModelWideParameterChangeEvent&lt;/identifier&gt;
        &lt;priority&gt;-1&lt;/priority&gt;
        &lt;schedulingClockId&gt;ParameterChangeEvent&lt;/schedulingClockId&gt;
      &lt;/rootTaskHierarchyElements&gt;
      &lt;rootTaskHierarchyElements type=&quot;sto.Task&quot; uuid=&quot;a74db072-2ee1-48ed-9094-03e3f88ca5db&quot;&gt;
        &lt;isExecutable&gt;true&lt;/isExecutable&gt;
        &lt;isExplicit&gt;true&lt;/isExplicit&gt;
        &lt;rates type=&quot;sto.ModelWideEventRate&quot; uuid=&quot;9ffd793d-d09c-4a8f-a330-40c755b5e936&quot;&gt;
          &lt;annotation&gt;Init&lt;/annotation&gt;
          &lt;clockId&gt;Init&lt;/clockId&gt;
          &lt;colorIndex&gt;10&lt;/colorIndex&gt;
          &lt;description&gt;初始化&lt;/description&gt;
          &lt;rateIdx&gt;2&lt;/rateIdx&gt;
          &lt;taskId&gt;ModelWideInitializeEvent&lt;/taskId&gt;
          &lt;rateSpec type=&quot;sto.RateSpec&quot; uuid=&quot;6113f7e9-4810-46a3-b4cb-1095fee89b7f&quot;&gt;
            &lt;offset&gt;1.0&lt;/offset&gt;
            &lt;period&gt;Inf&lt;/period&gt;
            &lt;rateType&gt;ModelWideInitializeEvent&lt;/rateType&gt;
          &lt;/rateSpec&gt;
        &lt;/rates&gt;
        &lt;tNum&gt;2&lt;/tNum&gt;
        &lt;elementType&gt;Task&lt;/elementType&gt;
        &lt;identifier&gt;ModelWideInitializeEvent&lt;/identifier&gt;
        &lt;priority&gt;-1&lt;/priority&gt;
        &lt;schedulingClockId&gt;Init&lt;/schedulingClockId&gt;
      &lt;/rootTaskHierarchyElements&gt;
      &lt;taskDependencyGraph type=&quot;sto.SerializedTaskConnectionList&quot; uuid=&quot;aa78153a-9476-49ee-bd06-e13d740a3acb&quot;&gt;
        &lt;taskIdentifier&gt;_task0&lt;/taskIdentifier&gt;
      &lt;/taskDependencyGraph&gt;
      &lt;taskDependencyGraph type=&quot;sto.SerializedTaskConnectionList&quot; uuid=&quot;7e68313b-7474-40b4-bee9-560bc084e347&quot;&gt;
        &lt;clockIdentifier&gt;Init&lt;/clockIdentifier&gt;
        &lt;taskIdentifier&gt;ModelWideInitializeEvent&lt;/taskIdentifier&gt;
      &lt;/taskDependencyGraph&gt;
      &lt;taskDependencyGraph type=&quot;sto.SerializedTaskConnectionList&quot; uuid=&quot;c816cc63-3b08-429b-9e67-d49d040e642a&quot;&gt;
        &lt;clockIdentifier&gt;ParameterChangeEvent&lt;/clockIdentifier&gt;
        &lt;taskIdentifier&gt;ModelWideParameterChangeEvent&lt;/taskIdentifier&gt;
      &lt;/taskDependencyGraph&gt;
      &lt;taskDependencyGraph type=&quot;sto.SerializedTaskConnectionList&quot; uuid=&quot;6224dc34-3500-43e9-a207-15fc7da09431&quot;&gt;
        &lt;taskIdentifier&gt;DHM_Step&lt;/taskIdentifier&gt;
      &lt;/taskDependencyGraph&gt;
    &lt;/taskRegistry&gt;
  &lt;/sto.Registry&gt;
&lt;/slexec_sto&gt;</timingAndTaskingRegistry>
    <zeroInternalMemoryAtStartupUnchecked>true</zeroInternalMemoryAtStartupUnchecked>
    <FMUBlockMap type="ModelRefInfoRepo.FMUBlockInfo" uuid="e282570c-a24a-4c29-8eef-df5df0b53e79"/>
    <codeGenInfo type="ModelRefInfoRepo.CodeGenInformation" uuid="cec609ff-428e-41c3-9c29-be905c7510ec"/>
    <compiledVariantInfos type="ModelRefInfoRepo.CompiledVariantInfoMap" uuid="4b07a082-6305-4558-b708-37cb6a2e0f66"/>
    <configSettingsForConsistencyChecks type="ModelRefInfoRepo.ConfigSettingsForConsistencyChecks" uuid="6aa2fa7c-e7ec-4f8e-acc8-dddc1611848d">
      <LUTObjectStructOrderEvenSpacing>1</LUTObjectStructOrderEvenSpacing>
      <consistentOutportInitialization>true</consistentOutportInitialization>
      <fixedStepSize>.01</fixedStepSize>
      <frameDiagnosticSetting>2</frameDiagnosticSetting>
      <hasHybridSampleTime>true</hasHybridSampleTime>
      <isExportFcnDiagram>true</isExportFcnDiagram>
      <isRateGrouped>true</isRateGrouped>
      <optimizedInitCode>true</optimizedInitCode>
      <signalLoggingSaveFormat>2</signalLoggingSaveFormat>
      <simSIMDOptimization>1</simSIMDOptimization>
      <solverMode>SOLVER_MODE_MULTITASKING</solverMode>
      <solverName>FixedStepDiscrete</solverName>
      <solverType>SOLVER_TYPE_FIXEDSTEP</solverType>
      <hardwareSettings type="ModelRefInfoRepo.HardwareSettings" uuid="81754fbe-890f-474f-afa6-366e6ee904ec">
        <prodBitPerChar>8</prodBitPerChar>
        <prodBitPerDouble>64</prodBitPerDouble>
        <prodBitPerFloat>32</prodBitPerFloat>
        <prodBitPerInt>32</prodBitPerInt>
        <prodBitPerLong>32</prodBitPerLong>
        <prodBitPerLongLong>64</prodBitPerLongLong>
        <prodBitPerPointer>64</prodBitPerPointer>
        <prodBitPerPtrDiffT>64</prodBitPerPtrDiffT>
        <prodBitPerShort>16</prodBitPerShort>
        <prodBitPerSizeT>64</prodBitPerSizeT>
        <prodEndianess>1</prodEndianess>
        <prodShiftRight>true</prodShiftRight>
        <prodWordSize>64</prodWordSize>
      </hardwareSettings>
    </configSettingsForConsistencyChecks>
    <controllableInputRatesMap type="ModelRefInfoRepo.VarTsUIDMap" uuid="a1611ccb-da5e-49fd-931f-e577ecd07a46"/>
    <controllableOutputRatesMap type="ModelRefInfoRepo.VarTsUIDMap" uuid="00ae807e-23a6-4917-93d3-1231a9715bfa"/>
    <dataPortGroup type="ModelRefInfoRepo.DataPortGroup" uuid="e638fdaa-a5bc-4613-833f-505aa05ada23"/>
    <expFcnUnconnectedDataPortGroup type="ModelRefInfoRepo.DataPortGroup" uuid="00349a56-a8e3-48af-b311-a79e9a41a708"/>
    <interfaceParameterInfo type="ModelRefInfoRepo.InterfaceParameterInfo" uuid="6d1401b6-8eb3-4224-95df-4dfb7c397ab1"/>
    <messageInfo type="ModelRefInfoRepo.MessageInformation" uuid="0e01b6da-b4ac-4dee-9b74-b8bb9ca35092">
      <rootInportInfo type="ModelRefInfoRepo.MessageRootPortInfo" uuid="2ba9204f-bff2-4134-a5d1-a8cada8be67a">
        <GrHierarchyMsgModeMap type="ModelRefInfoRepo.MessageModeMap" uuid="167cc378-b493-4f4e-8541-a5ffda0e7782">
          <portIdx>5</portIdx>
        </GrHierarchyMsgModeMap>
        <GrHierarchyMsgModeMap type="ModelRefInfoRepo.MessageModeMap" uuid="99986e23-ab3a-47f3-88a7-e25b78a92a76">
          <portIdx>6</portIdx>
        </GrHierarchyMsgModeMap>
      </rootInportInfo>
      <rootOutportInfo type="ModelRefInfoRepo.MessageRootPortInfo" uuid="8f4e0347-0b61-41ce-8e9f-3f2a984b0cb9">
        <GrHierarchyMsgModeMap type="ModelRefInfoRepo.MessageModeMap" uuid="7c669c14-78bf-4651-878d-fbbd6faff48d">
          <portIdx>10</portIdx>
        </GrHierarchyMsgModeMap>
        <GrHierarchyMsgModeMap type="ModelRefInfoRepo.MessageModeMap" uuid="06c1ebde-16a9-4761-bea5-e66398391365">
          <portIdx>11</portIdx>
        </GrHierarchyMsgModeMap>
      </rootOutportInfo>
    </messageInfo>
    <methodInfo type="ModelRefInfoRepo.MethodExistenceInfo" uuid="4a16f393-dc89-4309-a9d0-0d3ed8777372">
      <hasEnableMethod>true</hasEnableMethod>
      <hasSystemInitializeMethod>true</hasSystemInitializeMethod>
      <hasSystemResetMethod>true</hasSystemResetMethod>
      <hasTerminateMethod>true</hasTerminateMethod>
      <hasUpdateMethod>true</hasUpdateMethod>
    </methodInfo>
    <periodicEventPortUnsupportedBlockInfo type="ModelRefInfoRepo.PeriodicEventPortUnsupportedBlockInfo" uuid="90be6e2d-0bcc-481b-b825-a6452617441b"/>
    <portGroupsRequireSameRate type="ModelRefInfoRepo.PortGroupsRequireSameRate" uuid="16a8d714-ff59-4951-8823-e5d2e1c38e7b">
      <DSMPortGroups type="ModelRefInfoRepo.NameToPortGroupIdxVectMap" uuid="e57975e5-ce25-4280-a202-301afeba3acc"/>
      <GlobalDSMPortGroups type="ModelRefInfoRepo.NameToPortGroupIdxVectMap" uuid="57e81ee1-c948-42fe-bb5b-3c74143b95d8"/>
      <mergedPortGroups type="ModelRefInfoRepo.NameToPortGroupIdxVectMap" uuid="bbf65f62-5127-4277-b6a7-94b885ea8cfd"/>
    </portGroupsRequireSameRate>
    <rateBasedMdlGlobalDSMRateSpec type="ModelRefInfoRepo.GlobalDSMRateSpecMap" uuid="aaa9bf79-dbb1-473d-a972-08de8f1f952e"/>
    <rateSpecOfGlobalDSMAccessedByDescExpFcnMdlMap type="ModelRefInfoRepo.GlobalDSMRateSpecMap" uuid="12e8681f-48e9-4188-82d8-fc000ceeaf21"/>
    <rootBlockDiagramInterface type="ci.Model" uuid="afda9aae-08bb-448b-8aeb-4d0d6f05bae1">
      <p_RootComponentInterface type="ci.ComponentInterface" uuid="a06a3b84-87d1-471e-a6cf-8cc10cca4958">
        <p_InputPorts type="ci.SignalInterface" uuid="a3e1c55a-0534-419b-a3e8-8b42e2af30dc">
          <p_ComputedNumericDimensions>1.0</p_ComputedNumericDimensions>
          <p_ComputedSampleTime>.01</p_ComputedSampleTime>
          <p_ComputedSampleTime>0.0</p_ComputedSampleTime>
          <p_ComputedType>fcn_call</p_ComputedType>
        </p_InputPorts>
        <p_InputPorts type="ci.SignalInterface" uuid="0594765b-fe15-41ea-ba7e-fb3cf4d5891a">
          <p_ComputedNumericDimensions>1.0</p_ComputedNumericDimensions>
          <p_ComputedSampleTime>.01</p_ComputedSampleTime>
          <p_ComputedSampleTime>0.0</p_ComputedSampleTime>
          <p_ComputedType>SInt16</p_ComputedType>
        </p_InputPorts>
        <p_InputPorts type="ci.SignalInterface" uuid="d087ad2b-6a87-4a3a-89b0-cb0ee8a9b099">
          <p_ComputedNumericDimensions>1.0</p_ComputedNumericDimensions>
          <p_ComputedSampleTime>.01</p_ComputedSampleTime>
          <p_ComputedSampleTime>0.0</p_ComputedSampleTime>
          <p_ComputedType>SInt16</p_ComputedType>
        </p_InputPorts>
        <p_InputPorts type="ci.SignalInterface" uuid="3b25f076-239b-48b0-adec-76fb765aeec9">
          <p_ComputedNumericDimensions>1.0</p_ComputedNumericDimensions>
          <p_ComputedSampleTime>.01</p_ComputedSampleTime>
          <p_ComputedSampleTime>0.0</p_ComputedSampleTime>
          <p_ComputedType>UInt8</p_ComputedType>
        </p_InputPorts>
        <p_InputPorts type="ci.SignalInterface" uuid="15771930-1b82-4768-ade4-626eab2c1610">
          <p_ComputedNumericDimensions>1.0</p_ComputedNumericDimensions>
          <p_ComputedSampleTime>.01</p_ComputedSampleTime>
          <p_ComputedSampleTime>0.0</p_ComputedSampleTime>
          <p_ComputedType>UInt8</p_ComputedType>
        </p_InputPorts>
        <p_InputPorts type="ci.SignalInterface" uuid="6068f941-9062-47b8-ae19-73be5d601e0c">
          <p_ComputedNumericDimensions>1.0</p_ComputedNumericDimensions>
          <p_ComputedSampleTime>.01</p_ComputedSampleTime>
          <p_ComputedSampleTime>0.0</p_ComputedSampleTime>
          <p_ComputedType>SInt16</p_ComputedType>
        </p_InputPorts>
        <p_InputPorts type="ci.SignalInterface" uuid="40a59869-7eff-4562-9108-afc4d98144d6">
          <p_ComputedNumericDimensions>1.0</p_ComputedNumericDimensions>
          <p_ComputedSampleTime>.01</p_ComputedSampleTime>
          <p_ComputedSampleTime>0.0</p_ComputedSampleTime>
          <p_ComputedType>SInt16</p_ComputedType>
        </p_InputPorts>
        <p_InputPorts type="ci.SignalInterface" uuid="5a42060e-6fb3-4bf3-a5cc-35a24bb76abb">
          <p_ComputedNumericDimensions>1.0</p_ComputedNumericDimensions>
          <p_ComputedSampleTime>.01</p_ComputedSampleTime>
          <p_ComputedSampleTime>0.0</p_ComputedSampleTime>
          <p_ComputedType>Boolean</p_ComputedType>
        </p_InputPorts>
        <p_InputPorts type="ci.SignalInterface" uuid="ff2f2c4c-66a1-41ab-8843-9bc52df059db">
          <p_ComputedNumericDimensions>1.0</p_ComputedNumericDimensions>
          <p_ComputedSampleTime>.01</p_ComputedSampleTime>
          <p_ComputedSampleTime>0.0</p_ComputedSampleTime>
          <p_ComputedType>UInt8</p_ComputedType>
        </p_InputPorts>
        <p_InputPorts type="ci.SignalInterface" uuid="539f473f-d13a-4472-b814-5bf67cb1b50f">
          <p_ComputedNumericDimensions>1.0</p_ComputedNumericDimensions>
          <p_ComputedSampleTime>.01</p_ComputedSampleTime>
          <p_ComputedSampleTime>0.0</p_ComputedSampleTime>
          <p_ComputedType>UInt8</p_ComputedType>
        </p_InputPorts>
        <p_Name>DHM</p_Name>
        <p_OutputPorts type="ci.SignalInterface" uuid="27451e8c-3a5b-44ec-bf55-feaada53b7c2">
          <p_ComputedNumericDimensions>1.0</p_ComputedNumericDimensions>
          <p_ComputedSampleTime>.01</p_ComputedSampleTime>
          <p_ComputedSampleTime>0.0</p_ComputedSampleTime>
          <p_ComputedType>UInt8</p_ComputedType>
        </p_OutputPorts>
        <p_OutputPorts type="ci.SignalInterface" uuid="59c61ebb-35c1-4cf6-a69b-9cd466e92e2e">
          <p_ComputedNumericDimensions>1.0</p_ComputedNumericDimensions>
          <p_ComputedSampleTime>.01</p_ComputedSampleTime>
          <p_ComputedSampleTime>0.0</p_ComputedSampleTime>
          <p_ComputedType>UInt8</p_ComputedType>
        </p_OutputPorts>
        <p_OutputPorts type="ci.SignalInterface" uuid="abcb9167-d5ce-464c-b837-9053ac62f67f">
          <p_ComputedNumericDimensions>1.0</p_ComputedNumericDimensions>
          <p_ComputedSampleTime>.01</p_ComputedSampleTime>
          <p_ComputedSampleTime>0.0</p_ComputedSampleTime>
          <p_ComputedType>Boolean</p_ComputedType>
        </p_OutputPorts>
        <p_OutputPorts type="ci.SignalInterface" uuid="dc5705f8-5396-4482-b9ac-3350b0e4e1fc">
          <p_ComputedNumericDimensions>1.0</p_ComputedNumericDimensions>
          <p_ComputedSampleTime>.01</p_ComputedSampleTime>
          <p_ComputedSampleTime>0.0</p_ComputedSampleTime>
          <p_ComputedType>Boolean</p_ComputedType>
        </p_OutputPorts>
        <p_OutputPorts type="ci.SignalInterface" uuid="aa72fbb7-3a68-4065-8b42-92882ebd3164">
          <p_ComputedNumericDimensions>1.0</p_ComputedNumericDimensions>
          <p_ComputedSampleTime>.01</p_ComputedSampleTime>
          <p_ComputedSampleTime>0.0</p_ComputedSampleTime>
          <p_ComputedType>Boolean</p_ComputedType>
        </p_OutputPorts>
        <p_OutputPorts type="ci.SignalInterface" uuid="b9707155-f70f-400d-87f3-045d6061f165">
          <p_ComputedNumericDimensions>1.0</p_ComputedNumericDimensions>
          <p_ComputedSampleTime>.01</p_ComputedSampleTime>
          <p_ComputedSampleTime>0.0</p_ComputedSampleTime>
          <p_ComputedType>Boolean</p_ComputedType>
        </p_OutputPorts>
        <p_OutputPorts type="ci.SignalInterface" uuid="5847cf1c-ff4c-4787-aae6-0d97a49cf721">
          <p_ComputedNumericDimensions>1.0</p_ComputedNumericDimensions>
          <p_ComputedSampleTime>.01</p_ComputedSampleTime>
          <p_ComputedSampleTime>0.0</p_ComputedSampleTime>
          <p_ComputedType>SInt16</p_ComputedType>
        </p_OutputPorts>
        <p_OutputPorts type="ci.SignalInterface" uuid="c0bccad4-2d7e-44d9-86c5-966b911ab883">
          <p_ComputedNumericDimensions>1.0</p_ComputedNumericDimensions>
          <p_ComputedSampleTime>.01</p_ComputedSampleTime>
          <p_ComputedSampleTime>0.0</p_ComputedSampleTime>
          <p_ComputedType>SInt16</p_ComputedType>
        </p_OutputPorts>
        <p_OutputPorts type="ci.SignalInterface" uuid="5f9a47a9-31f9-4af0-82de-9a7716efc742">
          <p_ComputedNumericDimensions>1.0</p_ComputedNumericDimensions>
          <p_ComputedSampleTime>.01</p_ComputedSampleTime>
          <p_ComputedSampleTime>0.0</p_ComputedSampleTime>
          <p_ComputedType>UInt8</p_ComputedType>
        </p_OutputPorts>
        <p_OutputPorts type="ci.SignalInterface" uuid="39dc7213-93ea-4d5f-bcac-c5165da23b2f">
          <p_ComputedNumericDimensions>1.0</p_ComputedNumericDimensions>
          <p_ComputedSampleTime>.01</p_ComputedSampleTime>
          <p_ComputedSampleTime>0.0</p_ComputedSampleTime>
          <p_ComputedType>UInt8</p_ComputedType>
        </p_OutputPorts>
        <p_OutputPorts type="ci.SignalInterface" uuid="bac84d44-ee8d-4ccd-9509-7dc0bdfcee60">
          <p_ComputedNumericDimensions>1.0</p_ComputedNumericDimensions>
          <p_ComputedSampleTime>.01</p_ComputedSampleTime>
          <p_ComputedSampleTime>0.0</p_ComputedSampleTime>
          <p_ComputedType>UInt8</p_ComputedType>
        </p_OutputPorts>
        <p_OutputPorts type="ci.SignalInterface" uuid="0c744ccb-e090-41b1-b929-808f0bb42aaf">
          <p_ComputedNumericDimensions>1.0</p_ComputedNumericDimensions>
          <p_ComputedSampleTime>.01</p_ComputedSampleTime>
          <p_ComputedSampleTime>0.0</p_ComputedSampleTime>
          <p_ComputedType>UInt8</p_ComputedType>
        </p_OutputPorts>
        <p_Type>ROOT</p_Type>
      </p_RootComponentInterface>
    </rootBlockDiagramInterface>
    <simulinkFunctions type="ModelRefInfoRepo.SimulinkFunctions" uuid="f7ee8cb6-3b8f-4656-8939-9fffa5a66190">
      <compSimulinkFunctionCatalog></compSimulinkFunctionCatalog>
    </simulinkFunctions>
    <stateWriterToOwnerMap type="ModelRefInfoRepo.StateWriterInfo" uuid="9c9b2cbe-cc0d-463c-800b-ba493d82af9f"/>
    <stoClientDataRegistry type="sto.ClientDataRegistry" uuid="7e52ef49-4824-4867-b3a4-6d572011c1f8">
      <dataSets type="sto.ClientClockNamedDataSet" uuid="366efe21-c874-446e-a737-cdd0bb11e312">
        <tag>sltpEvents</tag>
      </dataSets>
      <dataSets type="sto.ClientTaskHierarchyElementNamedDataSet" uuid="2c97e753-b30f-4ac2-8170-f5b25c76a877">
        <tag>sltpTaskGroups</tag>
      </dataSets>
      <dataSets type="sto.ClientTaskHierarchyElementNamedDataSet" uuid="f8a89bd9-4d58-4ea7-bf10-14b71d5eb4ca">
        <dSet type="ModelRefInfoRepo.SltpTaskData" uuid="15c65a1f-89db-4787-b3f7-00451041541a"/>
        <tSet type="ModelRefInfoRepo.SltpTaskData" uuid="15c65a1f-89db-4787-b3f7-00451041541a">
          <dataName>DHM_Step</dataName>
          <linkedSet type="sto.ClientTaskHierarchyElementNamedDataSet" uuid="f8a89bd9-4d58-4ea7-bf10-14b71d5eb4ca"/>
          <id type="sto.TaskHierarchyElementId">
            <id>DHM_Step</id>
          </id>
        </tSet>
        <tag>sltpTasks</tag>
      </dataSets>
    </stoClientDataRegistry>
    <varTsUIDMap type="ModelRefInfoRepo.VarTsUIDMap" uuid="2c360e91-123d-4ab5-8e5b-e265c61c2cf5"/>
  </ModelRefInfoRepo.ModelRefInfoRoot>
</MF0>